bismarkplot/BismarkPlot.py
bismarkplot/__init__.py
bismarkplot/console_chrs.py
bismarkplot/console_metagene.py
bismarkplot-1.3.2.post3.dist-info/METADATA
bismarkplot-1.3.2.post3.dist-info/WHEEL
bismarkplot-1.3.2.post3.dist-info/entry_points.txt
bismarkplot-1.3.2.post3.dist-info/licenses/LICENSE.txt
bismarkplot-1.3.2.post3.dist-info/RECORD
