Metadata-Version: 2.1
Name: bismarkplot
Version: 1.3.2.post3
Summary: Analytical framework for BS-seq data comparison and visualization
Project-URL: Homepage, https://github.com/shitohana/BismarkPlot
Project-URL: Documentation, https://shitohana.github.io/BismarkPlot/
Project-URL: Bug Tracker, https://github.com/shitohana/BismarkPlot/issues
Author-email: shitohana <kyudytskiy@gmail.com>
License:                     GNU GENERAL PUBLIC LICENSE
License-File: LICENSE.txt
Keywords: bismark,bs-seq,methylation,plot
Classifier: License :: OSI Approved :: GNU General Public License v3 (GPLv3)
Classifier: Operating System :: OS Independent
Classifier: Programming Language :: Python :: 3
Requires-Python: >=3.9
Requires-Dist: dynamictreecut>=0.1.1
Requires-Dist: matplotlib>=3.7.1
Requires-Dist: numpy>=1.24.2
Requires-Dist: pandas>=2.0.0
Requires-Dist: polars>=0.17.5
Requires-Dist: pyarrow>=13.0.0
Requires-Dist: pyreadr>=0.4.9
Requires-Dist: scipy>=1.10.1
